{
  "library": "BACnet2",
  "title": "PreUnregister (Method)",
  "url": "https://content.helpme-codesys.com/en/libs/BACnet2/Current/BACnetServerPlugin/pou-IBACnetServerPlugin/PreUnregister.html",
  "page_title": "IBACnetServerPlugin.PreUnregister (METH)",
  "text": "\nMETHOD PreUnregister : UDINT\nDeinitialization, gets called during\nBACnetServer.UnregisterPlugin\nbefore application service hooks/callbacks are unregistered.\nReturn CmpErrors.Errors.ERR_OK if successfully.\n",
  "tables": [
    {
      "headers": [
        "Scope",
        "Name",
        "Type"
      ],
      "rows": [
        {
          "Scope": "Return",
          "Name": "PreUnregister",
          "Type": "UDINT"
        }
      ]
    }
  ]
}